kubedantic/__init__.py
kubedantic/py.typed
kubedantic/models/io/k8s/api/admissionregistration/__init__.py
kubedantic/models/io/k8s/api/admissionregistration/v1.py
kubedantic/models/io/k8s/api/admissionregistration/v1alpha1.py
kubedantic/models/io/k8s/api/admissionregistration/v1beta1.py
kubedantic/models/io/k8s/api/apps/__init__.py
kubedantic/models/io/k8s/api/apps/v1.py
kubedantic/models/io/k8s/api/authentication/__init__.py
kubedantic/models/io/k8s/api/authentication/v1.py
kubedantic/models/io/k8s/api/authentication/v1alpha1.py
kubedantic/models/io/k8s/api/authentication/v1beta1.py
kubedantic/models/io/k8s/api/authorization/__init__.py
kubedantic/models/io/k8s/api/authorization/v1.py
kubedantic/models/io/k8s/api/autoscaling/__init__.py
kubedantic/models/io/k8s/api/autoscaling/v1.py
kubedantic/models/io/k8s/api/autoscaling/v2.py
kubedantic/models/io/k8s/api/batch/__init__.py
kubedantic/models/io/k8s/api/batch/v1.py
kubedantic/models/io/k8s/api/certificates/__init__.py
kubedantic/models/io/k8s/api/certificates/v1.py
kubedantic/models/io/k8s/api/certificates/v1alpha1.py
kubedantic/models/io/k8s/api/coordination/__init__.py
kubedantic/models/io/k8s/api/coordination/v1.py
kubedantic/models/io/k8s/api/core/__init__.py
kubedantic/models/io/k8s/api/core/v1.py
kubedantic/models/io/k8s/api/discovery/__init__.py
kubedantic/models/io/k8s/api/discovery/v1.py
kubedantic/models/io/k8s/api/events/__init__.py
kubedantic/models/io/k8s/api/events/v1.py
kubedantic/models/io/k8s/api/flowcontrol/__init__.py
kubedantic/models/io/k8s/api/flowcontrol/v1.py
kubedantic/models/io/k8s/api/flowcontrol/v1beta3.py
kubedantic/models/io/k8s/api/networking/__init__.py
kubedantic/models/io/k8s/api/networking/v1.py
kubedantic/models/io/k8s/api/networking/v1alpha1.py
kubedantic/models/io/k8s/api/node/__init__.py
kubedantic/models/io/k8s/api/node/v1.py
kubedantic/models/io/k8s/api/policy/__init__.py
kubedantic/models/io/k8s/api/policy/v1.py
kubedantic/models/io/k8s/api/rbac/__init__.py
kubedantic-0.1.1.dist-info/LICENSE
kubedantic-0.1.1.dist-info/METADATA
kubedantic-0.1.1.dist-info/WHEEL
kubedantic-0.1.1.dist-info/top_level.txt
kubedantic-0.1.1.dist-info/RECORD
