Metadata-Version: 2.1
Name: kubedantic
Version: 0.1.1
Summary: Kubedantic - Pydantic models for Kubernetes
Author-email: Thiago Pena <thiagopena01@gmail.com>, Diogo Baeder <diogobaeder@yahoo.com.br>
Project-URL: Homepage, https://github.com/coherent-oss/kubedantic
Classifier: Development Status :: 5 - Production/Stable
Classifier: Intended Audience :: Developers
Classifier: License :: OSI Approved :: MIT License
Classifier: Programming Language :: Python :: 3
Classifier: Programming Language :: Python :: 3 :: Only
Requires-Python: >=3.8
License-File: LICENSE
Requires-Dist: pydantic >=2
Provides-Extra: docs
Requires-Dist: sphinx >=3.5 ; extra == 'docs'
Requires-Dist: jaraco.packaging >=9.3 ; extra == 'docs'
Requires-Dist: rst.linker >=1.9 ; extra == 'docs'
Requires-Dist: furo ; extra == 'docs'
Requires-Dist: sphinx-lint ; extra == 'docs'
Provides-Extra: generator
Requires-Dist: datamodel-code-generator >=0.25.5 ; extra == 'generator'
Requires-Dist: requests >=2.31.0 ; extra == 'generator'
Provides-Extra: testing
Requires-Dist: pytest !=8.1.*,>=6 ; extra == 'testing'
Requires-Dist: pytest-checkdocs >=2.4 ; extra == 'testing'
Requires-Dist: pytest-cov ; extra == 'testing'
Requires-Dist: pytest-mypy ; extra == 'testing'
Requires-Dist: pytest-enabler >=2.2 ; extra == 'testing'
Requires-Dist: pytest-ruff >=0.2.1 ; extra == 'testing'
Requires-Dist: freezegun >=1.5.0 ; extra == 'testing'
